// class version 50.0 (50)
// access flags 0x21
public class net/minecraft/nbt/NBTTagCompound extends net/minecraft/nbt/NBTBase  {

  // compiled from: NBTTagCompound.java
  // access flags 0x0
  INNERCLASS net/minecraft/nbt/NBTTagCompound$2 null null
  // access flags 0x0
  INNERCLASS net/minecraft/nbt/NBTTagCompound$1 null null
  // access flags 0x409
  public static abstract INNERCLASS net/minecraft/nbt/NBTBase$NBTPrimitive net/minecraft/nbt/NBTBase NBTPrimitive

  // access flags 0x1A
  private final static Lorg/apache/logging/log4j/Logger; logger

  // access flags 0x2
  private Ljava/util/Map; tagMap

  // access flags 0x1A
  private final static Ljava/lang/String; __OBFID = "CL_00001215"

  // access flags 0x1
  public <init>()V
   L0
    LINENUMBER 17 L0
    ALOAD 0
    INVOKESPECIAL net/minecraft/nbt/NBTBase.<init> ()V
   L1
    LINENUMBER 20 L1
    ALOAD 0
    INVOKESTATIC com/google/common/collect/Maps.newHashMap ()Ljava/util/HashMap;
    PUTFIELD net/minecraft/nbt/NBTTagCompound.tagMap : Ljava/util/Map;
    RETURN
   L2
    LOCALVARIABLE this Lnet/minecraft/nbt/NBTTagCompound; L0 L2 0
    MAXSTACK = 2
    MAXLOCALS = 1

  // access flags 0x0
  write(Ljava/io/DataOutput;)V throws java/io/IOException 
   L0
    LINENUMBER 25 L0
    ALOAD 0
    GETFIELD net/minecraft/nbt/NBTTagCompound.tagMap : Ljava/util/Map;
    INVOKEINTERFACE java/util/Map.keySet ()Ljava/util/Set;
    INVOKEINTERFACE java/util/Set.iterator ()Ljava/util/Iterator;
    ASTORE 2
   L1
    LINENUMBER 27 L1
   FRAME FULL [net/minecraft/nbt/NBTTagCompound java/io/DataOutput java/util/Iterator] []
    ALOAD 2
    INVOKEINTERFACE java/util/Iterator.hasNext ()Z
    IFEQ L2
   L3
    LINENUMBER 29 L3
    ALOAD 2
    INVOKEINTERFACE java/util/Iterator.next ()Ljava/lang/Object;
    CHECKCAST java/lang/String
    ASTORE 3
   L4
    LINENUMBER 30 L4
    ALOAD 0
    GETFIELD net/minecraft/nbt/NBTTagCompound.tagMap : Ljava/util/Map;
    ALOAD 3
    INVOKEINTERFACE java/util/Map.get (Ljava/lang/Object;)Ljava/lang/Object;
    CHECKCAST net/minecraft/nbt/NBTBase
    ASTORE 4
   L5
    LINENUMBER 31 L5
    ALOAD 3
    ALOAD 4
    ALOAD 1
    INVOKESTATIC net/minecraft/nbt/NBTTagCompound.writeEntry (Ljava/lang/String;Lnet/minecraft/nbt/NBTBase;Ljava/io/DataOutput;)V
   L6
    LINENUMBER 32 L6
    GOTO L1
   L2
    LINENUMBER 34 L2
   FRAME FULL [net/minecraft/nbt/NBTTagCompound java/io/DataOutput java/util/Iterator] []
    ALOAD 1
    ICONST_0
    INVOKEINTERFACE java/io/DataOutput.writeByte (I)V
   L7
    LINENUMBER 35 L7
    RETURN
   L8
    LOCALVARIABLE this Lnet/minecraft/nbt/NBTTagCompound; L0 L0 0
    LOCALVARIABLE p_write_1_ Ljava/io/DataOutput; L0 L0 1
    LOCALVARIABLE s Ljava/lang/String; L4 L6 3
    LOCALVARIABLE nbtbase Lnet/minecraft/nbt/NBTBase; L5 L6 4
    LOCALVARIABLE this Lnet/minecraft/nbt/NBTTagCompound; L0 L8 0
    LOCALVARIABLE output Ljava/io/DataOutput; L0 L8 1
    LOCALVARIABLE iterator Ljava/util/Iterator; L1 L8 2
    MAXSTACK = 3
    MAXLOCALS = 5

  // access flags 0x0
  read(Ljava/io/DataInput;ILnet/minecraft/nbt/NBTSizeTracker;)V throws java/io/IOException 
   L0
    LINENUMBER 39 L0
    ILOAD 2
    SIPUSH 512
    IF_ICMPLE L1
   L2
    LINENUMBER 41 L2
    NEW java/lang/RuntimeException
    DUP
    LDC "Tried to read NBT tag with too high complexity, depth > 512"
    INVOKESPECIAL java/lang/RuntimeException.<init> (Ljava/lang/String;)V
    ATHROW
   L1
    LINENUMBER 45 L1
   FRAME FULL [net/minecraft/nbt/NBTTagCompound java/io/DataInput I net/minecraft/nbt/NBTSizeTracker] []
    ALOAD 0
    GETFIELD net/minecraft/nbt/NBTTagCompound.tagMap : Ljava/util/Map;
    INVOKEINTERFACE java/util/Map.clear ()V
   L3
    LINENUMBER 48 L3
   FRAME FULL [net/minecraft/nbt/NBTTagCompound java/io/DataInput I net/minecraft/nbt/NBTSizeTracker] []
    ALOAD 1
    ALOAD 3
    INVOKESTATIC net/minecraft/nbt/NBTTagCompound.readType (Ljava/io/DataInput;Lnet/minecraft/nbt/NBTSizeTracker;)B
    DUP
    ISTORE 4
   L4
    IFEQ L5
   L6
    LINENUMBER 50 L6
    ALOAD 1
    ALOAD 3
    INVOKESTATIC net/minecraft/nbt/NBTTagCompound.readKey (Ljava/io/DataInput;Lnet/minecraft/nbt/NBTSizeTracker;)Ljava/lang/String;
    ASTORE 5
   L7
    LINENUMBER 51 L7
    ALOAD 3
    ALOAD 5
    INVOKESTATIC net/minecraft/nbt/NBTSizeTracker.readUTF (Lnet/minecraft/nbt/NBTSizeTracker;Ljava/lang/String;)V
   L8
    LINENUMBER 52 L8
    ILOAD 4
    ALOAD 5
    ALOAD 1
    ILOAD 2
    ICONST_1
    IADD
    ALOAD 3
    INVOKESTATIC net/minecraft/nbt/NBTTagCompound.readNBT (BLjava/lang/String;Ljava/io/DataInput;ILnet/minecraft/nbt/NBTSizeTracker;)Lnet/minecraft/nbt/NBTBase;
    ASTORE 6
   L9
    LINENUMBER 53 L9
    ALOAD 0
    GETFIELD net/minecraft/nbt/NBTTagCompound.tagMap : Ljava/util/Map;
    ALOAD 5
    ALOAD 6
    INVOKEINTERFACE java/util/Map.put (Ljava/lang/Object;Ljava/lang/Object;)Ljava/lang/Object;
    POP
   L10
    LINENUMBER 54 L10
    GOTO L3
   L5
    LINENUMBER 56 L5
   FRAME FULL [net/minecraft/nbt/NBTTagCompound java/io/DataInput I net/minecraft/nbt/NBTSizeTracker I] []
    RETURN
   L11
    LOCALVARIABLE this Lnet/minecraft/nbt/NBTTagCompound; L0 L0 0
    LOCALVARIABLE p_read_1_ Ljava/io/DataInput; L0 L0 1
    LOCALVARIABLE p_read_2_ I L0 L0 2
    LOCALVARIABLE p_read_3_ Lnet/minecraft/nbt/NBTSizeTracker; L0 L0 3
    LOCALVARIABLE s Ljava/lang/String; L7 L10 5
    LOCALVARIABLE nbtbase Lnet/minecraft/nbt/NBTBase; L9 L10 6
    LOCALVARIABLE b0 B L4 L5 4
    LOCALVARIABLE this Lnet/minecraft/nbt/NBTTagCompound; L0 L11 0
    LOCALVARIABLE input Ljava/io/DataInput; L0 L11 1
    LOCALVARIABLE depth I L0 L11 2
    LOCALVARIABLE sizeTracker Lnet/minecraft/nbt/NBTSizeTracker; L0 L11 3
    MAXSTACK = 5
    MAXLOCALS = 7

  // access flags 0x1
  public getKeySet()Ljava/util/Set;
   L0
    LINENUMBER 60 L0
    ALOAD 0
    GETFIELD net/minecraft/nbt/NBTTagCompound.tagMap : Ljava/util/Map;
    INVOKEINTERFACE java/util/Map.keySet ()Ljava/util/Set;
    ARETURN
   L1
    LOCALVARIABLE this Lnet/minecraft/nbt/NBTTagCompound; L0 L1 0
    MAXSTACK = 1
    MAXLOCALS = 1

  // access flags 0x1
  public getId()B
   L0
    LINENUMBER 65 L0
    BIPUSH 10
    IRETURN
   L1
    LOCALVARIABLE this Lnet/minecraft/nbt/NBTTagCompound; L0 L1 0
    MAXSTACK = 1
    MAXLOCALS = 1

  // access flags 0x1
  public setTag(Ljava/lang/String;Lnet/minecraft/nbt/NBTBase;)V
   L0
    LINENUMBER 70 L0
    ALOAD 0
    GETFIELD net/minecraft/nbt/NBTTagCompound.tagMap : Ljava/util/Map;
    ALOAD 1
    ALOAD 2
    INVOKEINTERFACE java/util/Map.put (Ljava/lang/Object;Ljava/lang/Object;)Ljava/lang/Object;
    POP
   L1
    LINENUMBER 71 L1
    RETURN
   L2
    LOCALVARIABLE this Lnet/minecraft/nbt/NBTTagCompound; L0 L0 0
    LOCALVARIABLE p_setTag_1_ Ljava/lang/String; L0 L0 1
    LOCALVARIABLE p_setTag_2_ Lnet/minecraft/nbt/NBTBase; L0 L0 2
    LOCALVARIABLE this Lnet/minecraft/nbt/NBTTagCompound; L0 L2 0
    LOCALVARIABLE key Ljava/lang/String; L0 L2 1
    LOCALVARIABLE value Lnet/minecraft/nbt/NBTBase; L0 L2 2
    MAXSTACK = 3
    MAXLOCALS = 3

  // access flags 0x1
  public setByte(Ljava/lang/String;B)V
   L0
    LINENUMBER 75 L0
    ALOAD 0
    GETFIELD net/minecraft/nbt/NBTTagCompound.tagMap : Ljava/util/Map;
    ALOAD 1
    NEW net/minecraft/nbt/NBTTagByte
    DUP
    ILOAD 2
    INVOKESPECIAL net/minecraft/nbt/NBTTagByte.<init> (B)V
    INVOKEINTERFACE java/util/Map.put (Ljava/lang/Object;Ljava/lang/Object;)Ljava/lang/Object;
    POP
   L1
    LINENUMBER 76 L1
    RETURN
   L2
    LOCALVARIABLE this Lnet/minecraft/nbt/NBTTagCompound; L0 L0 0
    LOCALVARIABLE p_setByte_1_ Ljava/lang/String; L0 L0 1
    LOCALVARIABLE p_setByte_2_ B L0 L0 2
    LOCALVARIABLE this Lnet/minecraft/nbt/NBTTagCompound; L0 L2 0
    LOCALVARIABLE key Ljava/lang/String; L0 L2 1
    LOCALVARIABLE value B L0 L2 2
    MAXSTACK = 5
    MAXLOCALS = 3

  // access flags 0x1
  public setShort(Ljava/lang/String;S)V
   L0
    LINENUMBER 80 L0
    ALOAD 0
    GETFIELD net/minecraft/nbt/NBTTagCompound.tagMap : Ljava/util/Map;
    ALOAD 1
    NEW net/minecraft/nbt/NBTTagShort
    DUP
    ILOAD 2
    INVOKESPECIAL net/minecraft/nbt/NBTTagShort.<init> (S)V
    INVOKEINTERFACE java/util/Map.put (Ljava/lang/Object;Ljava/lang/Object;)Ljava/lang/Object;
    POP
   L1
    LINENUMBER 81 L1
    RETURN
   L2
    LOCALVARIABLE this Lnet/minecraft/nbt/NBTTagCompound; L0 L0 0
    LOCALVARIABLE p_setShort_1_ Ljava/lang/String; L0 L0 1
    LOCALVARIABLE p_setShort_2_ S L0 L0 2
    LOCALVARIABLE this Lnet/minecraft/nbt/NBTTagCompound; L0 L2 0
    LOCALVARIABLE key Ljava/lang/String; L0 L2 1
    LOCALVARIABLE value S L0 L2 2
    MAXSTACK = 5
    MAXLOCALS = 3

  // access flags 0x1
  public setInteger(Ljava/lang/String;I)V
   L0
    LINENUMBER 85 L0
    ALOAD 0
    GETFIELD net/minecraft/nbt/NBTTagCompound.tagMap : Ljava/util/Map;
    ALOAD 1
    NEW net/minecraft/nbt/NBTTagInt
    DUP
    ILOAD 2
    INVOKESPECIAL net/minecraft/nbt/NBTTagInt.<init> (I)V
    INVOKEINTERFACE java/util/Map.put (Ljava/lang/Object;Ljava/lang/Object;)Ljava/lang/Object;
    POP
   L1
    LINENUMBER 86 L1
    RETURN
   L2
    LOCALVARIABLE this Lnet/minecraft/nbt/NBTTagCompound; L0 L0 0
    LOCALVARIABLE p_setInteger_1_ Ljava/lang/String; L0 L0 1
    LOCALVARIABLE p_setInteger_2_ I L0 L0 2
    LOCALVARIABLE this Lnet/minecraft/nbt/NBTTagCompound; L0 L2 0
    LOCALVARIABLE key Ljava/lang/String; L0 L2 1
    LOCALVARIABLE value I L0 L2 2
    MAXSTACK = 5
    MAXLOCALS = 3

  // access flags 0x1
  public setLong(Ljava/lang/String;J)V
   L0
    LINENUMBER 90 L0
    ALOAD 0
    GETFIELD net/minecraft/nbt/NBTTagCompound.tagMap : Ljava/util/Map;
    ALOAD 1
    NEW net/minecraft/nbt/NBTTagLong
    DUP
    LLOAD 2
    INVOKESPECIAL net/minecraft/nbt/NBTTagLong.<init> (J)V
    INVOKEINTERFACE java/util/Map.put (Ljava/lang/Object;Ljava/lang/Object;)Ljava/lang/Object;
    POP
   L1
    LINENUMBER 91 L1
    RETURN
   L2
    LOCALVARIABLE this Lnet/minecraft/nbt/NBTTagCompound; L0 L0 0
    LOCALVARIABLE p_setLong_1_ Ljava/lang/String; L0 L0 1
    LOCALVARIABLE p_setLong_2_ J L0 L0 2
    LOCALVARIABLE this Lnet/minecraft/nbt/NBTTagCompound; L0 L2 0
    LOCALVARIABLE key Ljava/lang/String; L0 L2 1
    LOCALVARIABLE value J L0 L2 2
    MAXSTACK = 6
    MAXLOCALS = 4

  // access flags 0x1
  public setFloat(Ljava/lang/String;F)V
   L0
    LINENUMBER 95 L0
    ALOAD 0
    GETFIELD net/minecraft/nbt/NBTTagCompound.tagMap : Ljava/util/Map;
    ALOAD 1
    NEW net/minecraft/nbt/NBTTagFloat
    DUP
    FLOAD 2
    INVOKESPECIAL net/minecraft/nbt/NBTTagFloat.<init> (F)V
    INVOKEINTERFACE java/util/Map.put (Ljava/lang/Object;Ljava/lang/Object;)Ljava/lang/Object;
    POP
   L1
    LINENUMBER 96 L1
    RETURN
   L2
    LOCALVARIABLE this Lnet/minecraft/nbt/NBTTagCompound; L0 L0 0
    LOCALVARIABLE p_setFloat_1_ Ljava/lang/String; L0 L0 1
    LOCALVARIABLE p_setFloat_2_ F L0 L0 2
    LOCALVARIABLE this Lnet/minecraft/nbt/NBTTagCompound; L0 L2 0
    LOCALVARIABLE key Ljava/lang/String; L0 L2 1
    LOCALVARIABLE value F L0 L2 2
    MAXSTACK = 5
    MAXLOCALS = 3

  // access flags 0x1
  public setDouble(Ljava/lang/String;D)V
   L0
    LINENUMBER 100 L0
    ALOAD 0
    GETFIELD net/minecraft/nbt/NBTTagCompound.tagMap : Ljava/util/Map;
    ALOAD 1
    NEW net/minecraft/nbt/NBTTagDouble
    DUP
    DLOAD 2
    INVOKESPECIAL net/minecraft/nbt/NBTTagDouble.<init> (D)V
    INVOKEINTERFACE java/util/Map.put (Ljava/lang/Object;Ljava/lang/Object;)Ljava/lang/Object;
    POP
   L1
    LINENUMBER 101 L1
    RETURN
   L2
    LOCALVARIABLE this Lnet/minecraft/nbt/NBTTagCompound; L0 L0 0
    LOCALVARIABLE p_setDouble_1_ Ljava/lang/String; L0 L0 1
    LOCALVARIABLE p_setDouble_2_ D L0 L0 2
    LOCALVARIABLE this Lnet/minecraft/nbt/NBTTagCompound; L0 L2 0
    LOCALVARIABLE key Ljava/lang/String; L0 L2 1
    LOCALVARIABLE value D L0 L2 2
    MAXSTACK = 6
    MAXLOCALS = 4

  // access flags 0x1
  public setString(Ljava/lang/String;Ljava/lang/String;)V
   L0
    LINENUMBER 105 L0
    ALOAD 0
    GETFIELD net/minecraft/nbt/NBTTagCompound.tagMap : Ljava/util/Map;
    ALOAD 1
    NEW net/minecraft/nbt/NBTTagString
    DUP
    ALOAD 2
    INVOKESPECIAL net/minecraft/nbt/NBTTagString.<init> (Ljava/lang/String;)V
    INVOKEINTERFACE java/util/Map.put (Ljava/lang/Object;Ljava/lang/Object;)Ljava/lang/Object;
    POP
   L1
    LINENUMBER 106 L1
    RETURN
   L2
    LOCALVARIABLE this Lnet/minecraft/nbt/NBTTagCompound; L0 L0 0
    LOCALVARIABLE p_setString_1_ Ljava/lang/String; L0 L0 1
    LOCALVARIABLE p_setString_2_ Ljava/lang/String; L0 L0 2
    LOCALVARIABLE this Lnet/minecraft/nbt/NBTTagCompound; L0 L2 0
    LOCALVARIABLE key Ljava/lang/String; L0 L2 1
    LOCALVARIABLE value Ljava/lang/String; L0 L2 2
    MAXSTACK = 5
    MAXLOCALS = 3

  // access flags 0x1
  public setByteArray(Ljava/lang/String;[B)V
   L0
    LINENUMBER 110 L0
    ALOAD 0
    GETFIELD net/minecraft/nbt/NBTTagCompound.tagMap : Ljava/util/Map;
    ALOAD 1
    NEW net/minecraft/nbt/NBTTagByteArray
    DUP
    ALOAD 2
    INVOKESPECIAL net/minecraft/nbt/NBTTagByteArray.<init> ([B)V
    INVOKEINTERFACE java/util/Map.put (Ljava/lang/Object;Ljava/lang/Object;)Ljava/lang/Object;
    POP
   L1
    LINENUMBER 111 L1
    RETURN
   L2
    LOCALVARIABLE this Lnet/minecraft/nbt/NBTTagCompound; L0 L0 0
    LOCALVARIABLE p_setByteArray_1_ Ljava/lang/String; L0 L0 1
    LOCALVARIABLE p_setByteArray_2_ [B L0 L0 2
    LOCALVARIABLE this Lnet/minecraft/nbt/NBTTagCompound; L0 L2 0
    LOCALVARIABLE key Ljava/lang/String; L0 L2 1
    LOCALVARIABLE value [B L0 L2 2
    MAXSTACK = 5
    MAXLOCALS = 3

  // access flags 0x1
  public setIntArray(Ljava/lang/String;[I)V
   L0
    LINENUMBER 115 L0
    ALOAD 0
    GETFIELD net/minecraft/nbt/NBTTagCompound.tagMap : Ljava/util/Map;
    ALOAD 1
    NEW net/minecraft/nbt/NBTTagIntArray
    DUP
    ALOAD 2
    INVOKESPECIAL net/minecraft/nbt/NBTTagIntArray.<init> ([I)V
    INVOKEINTERFACE java/util/Map.put (Ljava/lang/Object;Ljava/lang/Object;)Ljava/lang/Object;
    POP
   L1
    LINENUMBER 116 L1
    RETURN
   L2
    LOCALVARIABLE this Lnet/minecraft/nbt/NBTTagCompound; L0 L0 0
    LOCALVARIABLE p_setIntArray_1_ Ljava/lang/String; L0 L0 1
    LOCALVARIABLE p_setIntArray_2_ [I L0 L0 2
    LOCALVARIABLE this Lnet/minecraft/nbt/NBTTagCompound; L0 L2 0
    LOCALVARIABLE key Ljava/lang/String; L0 L2 1
    LOCALVARIABLE value [I L0 L2 2
    MAXSTACK = 5
    MAXLOCALS = 3

  // access flags 0x1
  public setBoolean(Ljava/lang/String;Z)V
   L0
    LINENUMBER 120 L0
    ALOAD 0
    ALOAD 1
    ILOAD 2
    IFEQ L1
    ICONST_1
    GOTO L2
   L1
   FRAME FULL [net/minecraft/nbt/NBTTagCompound java/lang/String I] [net/minecraft/nbt/NBTTagCompound java/lang/String]
    ICONST_0
   L2
   FRAME FULL [net/minecraft/nbt/NBTTagCompound java/lang/String I] [net/minecraft/nbt/NBTTagCompound java/lang/String I]
    I2B
    INVOKEVIRTUAL net/minecraft/nbt/NBTTagCompound.setByte (Ljava/lang/String;B)V
   L3
    LINENUMBER 121 L3
    RETURN
   L4
    LOCALVARIABLE this Lnet/minecraft/nbt/NBTTagCompound; L0 L0 0
    LOCALVARIABLE p_setBoolean_1_ Ljava/lang/String; L0 L0 1
    LOCALVARIABLE p_setBoolean_2_ Z L0 L0 2
    LOCALVARIABLE this Lnet/minecraft/nbt/NBTTagCompound; L0 L4 0
    LOCALVARIABLE key Ljava/lang/String; L0 L4 1
    LOCALVARIABLE value Z L0 L4 2
    MAXSTACK = 3
    MAXLOCALS = 3

  // access flags 0x1
  public getTag(Ljava/lang/String;)Lnet/minecraft/nbt/NBTBase;
   L0
    LINENUMBER 125 L0
    ALOAD 0
    GETFIELD net/minecraft/nbt/NBTTagCompound.tagMap : Ljava/util/Map;
    ALOAD 1
    INVOKEINTERFACE java/util/Map.get (Ljava/lang/Object;)Ljava/lang/Object;
    CHECKCAST net/minecraft/nbt/NBTBase
    ARETURN
   L1
    LOCALVARIABLE this Lnet/minecraft/nbt/NBTTagCompound; L0 L0 0
    LOCALVARIABLE p_getTag_1_ Ljava/lang/String; L0 L0 1
    LOCALVARIABLE this Lnet/minecraft/nbt/NBTTagCompound; L0 L1 0
    LOCALVARIABLE key Ljava/lang/String; L0 L1 1
    MAXSTACK = 2
    MAXLOCALS = 2

  // access flags 0x1
  public getTagId(Ljava/lang/String;)B
   L0
    LINENUMBER 130 L0
    ALOAD 0
    GETFIELD net/minecraft/nbt/NBTTagCompound.tagMap : Ljava/util/Map;
    ALOAD 1
    INVOKEINTERFACE java/util/Map.get (Ljava/lang/Object;)Ljava/lang/Object;
    CHECKCAST net/minecraft/nbt/NBTBase
    ASTORE 2
   L1
    LINENUMBER 131 L1
    ALOAD 2
    IFNULL L2
    ALOAD 2
    INVOKEVIRTUAL net/minecraft/nbt/NBTBase.getId ()B
    GOTO L3
   L2
   FRAME FULL [net/minecraft/nbt/NBTTagCompound java/lang/String net/minecraft/nbt/NBTBase] []
    ICONST_0
   L3
   FRAME FULL [net/minecraft/nbt/NBTTagCompound java/lang/String net/minecraft/nbt/NBTBase] [I]
    IRETURN
   L4
    LOCALVARIABLE this Lnet/minecraft/nbt/NBTTagCompound; L0 L0 0
    LOCALVARIABLE p_getTagId_1_ Ljava/lang/String; L0 L0 1
    LOCALVARIABLE this Lnet/minecraft/nbt/NBTTagCompound; L0 L4 0
    LOCALVARIABLE key Ljava/lang/String; L0 L4 1
    LOCALVARIABLE nbtbase Lnet/minecraft/nbt/NBTBase; L1 L4 2
    MAXSTACK = 2
    MAXLOCALS = 3

  // access flags 0x1
  public hasKey(Ljava/lang/String;)Z
   L0
    LINENUMBER 136 L0
    ALOAD 0
    GETFIELD net/minecraft/nbt/NBTTagCompound.tagMap : Ljava/util/Map;
    ALOAD 1
    INVOKEINTERFACE java/util/Map.containsKey (Ljava/lang/Object;)Z
    IRETURN
   L1
    LOCALVARIABLE this Lnet/minecraft/nbt/NBTTagCompound; L0 L0 0
    LOCALVARIABLE p_hasKey_1_ Ljava/lang/String; L0 L0 1
    LOCALVARIABLE this Lnet/minecraft/nbt/NBTTagCompound; L0 L1 0
    LOCALVARIABLE key Ljava/lang/String; L0 L1 1
    MAXSTACK = 2
    MAXLOCALS = 2

  // access flags 0x1
  public hasKey(Ljava/lang/String;I)Z
   L0
    LINENUMBER 141 L0
    ALOAD 0
    ALOAD 1
    INVOKEVIRTUAL net/minecraft/nbt/NBTTagCompound.getTagId (Ljava/lang/String;)B
    ISTORE 3
   L1
    LINENUMBER 143 L1
    ILOAD 3
    ILOAD 2
    IF_ICMPNE L2
   L3
    LINENUMBER 145 L3
    ICONST_1
    IRETURN
   L2
    LINENUMBER 147 L2
   FRAME FULL [net/minecraft/nbt/NBTTagCompound java/lang/String I I] []
    ILOAD 2
    BIPUSH 99
    IF_ICMPEQ L4
   L5
    LINENUMBER 149 L5
    ILOAD 3
    IFLE L6
   L6
    LINENUMBER 154 L6
   FRAME FULL [net/minecraft/nbt/NBTTagCompound java/lang/String I I] []
    ICONST_0
    IRETURN
   L4
    LINENUMBER 158 L4
   FRAME FULL [net/minecraft/nbt/NBTTagCompound java/lang/String I I] []
    ILOAD 3
    ICONST_1
    IF_ICMPEQ L7
    ILOAD 3
    ICONST_2
    IF_ICMPEQ L7
    ILOAD 3
    ICONST_3
    IF_ICMPEQ L7
    ILOAD 3
    ICONST_4
    IF_ICMPEQ L7
    ILOAD 3
    ICONST_5
    IF_ICMPEQ L7
    ILOAD 3
    BIPUSH 6
    IF_ICMPNE L8
   L7
   FRAME FULL [net/minecraft/nbt/NBTTagCompound java/lang/String I I] []
    ICONST_1
    GOTO L9
   L8
   FRAME FULL [net/minecraft/nbt/NBTTagCompound java/lang/String I I] []
    ICONST_0
   L9
   FRAME FULL [net/minecraft/nbt/NBTTagCompound java/lang/String I I] [I]
    IRETURN
   L10
    LOCALVARIABLE this Lnet/minecraft/nbt/NBTTagCompound; L0 L0 0
    LOCALVARIABLE p_hasKey_1_ Ljava/lang/String; L0 L0 1
    LOCALVARIABLE p_hasKey_2_ I L0 L0 2
    LOCALVARIABLE this Lnet/minecraft/nbt/NBTTagCompound; L0 L10 0
    LOCALVARIABLE key Ljava/lang/String; L0 L10 1
    LOCALVARIABLE type I L0 L10 2
    LOCALVARIABLE b0 B L1 L10 3
    MAXSTACK = 2
    MAXLOCALS = 4

  // access flags 0x1
  public getByte(Ljava/lang/String;)B
    TRYCATCHBLOCK L0 L1 L2 java/lang/ClassCastException
   L0
    LINENUMBER 166 L0
    ALOAD 0
    ALOAD 1
    BIPUSH 99
    INVOKEVIRTUAL net/minecraft/nbt/NBTTagCompound.hasKey (Ljava/lang/String;I)Z
    IFNE L3
    ICONST_0
    GOTO L1
   L3
   FRAME FULL [net/minecraft/nbt/NBTTagCompound java/lang/String] []
    ALOAD 0
    GETFIELD net/minecraft/nbt/NBTTagCompound.tagMap : Ljava/util/Map;
    ALOAD 1
    INVOKEINTERFACE java/util/Map.get (Ljava/lang/Object;)Ljava/lang/Object;
    CHECKCAST net/minecraft/nbt/NBTBase$NBTPrimitive
    INVOKEVIRTUAL net/minecraft/nbt/NBTBase$NBTPrimitive.getByte ()B
   L1
   FRAME FULL [net/minecraft/nbt/NBTTagCompound java/lang/String] [I]
    IRETURN
   L2
    LINENUMBER 168 L2
   FRAME FULL [net/minecraft/nbt/NBTTagCompound java/lang/String] [java/lang/ClassCastException]
    ASTORE 2
   L4
    LINENUMBER 170 L4
    ICONST_0
    IRETURN
   L5
    LOCALVARIABLE this Lnet/minecraft/nbt/NBTTagCompound; L0 L0 0
    LOCALVARIABLE p_getByte_1_ Ljava/lang/String; L0 L0 1
    LOCALVARIABLE classcastexception Ljava/lang/ClassCastException; L4 L5 2
    LOCALVARIABLE this Lnet/minecraft/nbt/NBTTagCompound; L0 L5 0
    LOCALVARIABLE key Ljava/lang/String; L0 L5 1
    MAXSTACK = 3
    MAXLOCALS = 3

  // access flags 0x1
  public getShort(Ljava/lang/String;)S
    TRYCATCHBLOCK L0 L1 L2 java/lang/ClassCastException
   L0
    LINENUMBER 178 L0
    ALOAD 0
    ALOAD 1
    BIPUSH 99
    INVOKEVIRTUAL net/minecraft/nbt/NBTTagCompound.hasKey (Ljava/lang/String;I)Z
    IFNE L3
    ICONST_0
    GOTO L1
   L3
   FRAME FULL [net/minecraft/nbt/NBTTagCompound java/lang/String] []
    ALOAD 0
    GETFIELD net/minecraft/nbt/NBTTagCompound.tagMap : Ljava/util/Map;
    ALOAD 1
    INVOKEINTERFACE java/util/Map.get (Ljava/lang/Object;)Ljava/lang/Object;
    CHECKCAST net/minecraft/nbt/NBTBase$NBTPrimitive
    INVOKEVIRTUAL net/minecraft/nbt/NBTBase$NBTPrimitive.getShort ()S
   L1
   FRAME FULL [net/minecraft/nbt/NBTTagCompound java/lang/String] [I]
    IRETURN
   L2
    LINENUMBER 180 L2
   FRAME FULL [net/minecraft/nbt/NBTTagCompound java/lang/String] [java/lang/ClassCastException]
    ASTORE 2
   L4
    LINENUMBER 182 L4
    ICONST_0
    IRETURN
   L5
    LOCALVARIABLE this Lnet/minecraft/nbt/NBTTagCompound; L0 L0 0
    LOCALVARIABLE p_getShort_1_ Ljava/lang/String; L0 L0 1
    LOCALVARIABLE classcastexception Ljava/lang/ClassCastException; L4 L5 2
    LOCALVARIABLE this Lnet/minecraft/nbt/NBTTagCompound; L0 L5 0
    LOCALVARIABLE key Ljava/lang/String; L0 L5 1
    MAXSTACK = 3
    MAXLOCALS = 3

  // access flags 0x1
  public getInteger(Ljava/lang/String;)I
    TRYCATCHBLOCK L0 L1 L2 java/lang/ClassCastException
   L0
    LINENUMBER 190 L0
    ALOAD 0
    ALOAD 1
    BIPUSH 99
    INVOKEVIRTUAL net/minecraft/nbt/NBTTagCompound.hasKey (Ljava/lang/String;I)Z
    IFNE L3
    ICONST_0
    GOTO L1
   L3
   FRAME FULL [net/minecraft/nbt/NBTTagCompound java/lang/String] []
    ALOAD 0
    GETFIELD net/minecraft/nbt/NBTTagCompound.tagMap : Ljava/util/Map;
    ALOAD 1
    INVOKEINTERFACE java/util/Map.get (Ljava/lang/Object;)Ljava/lang/Object;
    CHECKCAST net/minecraft/nbt/NBTBase$NBTPrimitive
    INVOKEVIRTUAL net/minecraft/nbt/NBTBase$NBTPrimitive.getInt ()I
   L1
   FRAME FULL [net/minecraft/nbt/NBTTagCompound java/lang/String] [I]
    IRETURN
   L2
    LINENUMBER 192 L2
   FRAME FULL [net/minecraft/nbt/NBTTagCompound java/lang/String] [java/lang/ClassCastException]
    ASTORE 2
   L4
    LINENUMBER 194 L4
    ICONST_0
    IRETURN
   L5
    LOCALVARIABLE this Lnet/minecraft/nbt/NBTTagCompound; L0 L0 0
    LOCALVARIABLE p_getInteger_1_ Ljava/lang/String; L0 L0 1
    LOCALVARIABLE classcastexception Ljava/lang/ClassCastException; L4 L5 2
    LOCALVARIABLE this Lnet/minecraft/nbt/NBTTagCompound; L0 L5 0
    LOCALVARIABLE key Ljava/lang/String; L0 L5 1
    MAXSTACK = 3
    MAXLOCALS = 3

  // access flags 0x1
  public getLong(Ljava/lang/String;)J
    TRYCATCHBLOCK L0 L1 L2 java/lang/ClassCastException
   L0
    LINENUMBER 202 L0
    ALOAD 0
    ALOAD 1
    BIPUSH 99
    INVOKEVIRTUAL net/minecraft/nbt/NBTTagCompound.hasKey (Ljava/lang/String;I)Z
    IFNE L3
    LCONST_0
    GOTO L1
   L3
   FRAME FULL [net/minecraft/nbt/NBTTagCompound java/lang/String] []
    ALOAD 0
    GETFIELD net/minecraft/nbt/NBTTagCompound.tagMap : Ljava/util/Map;
    ALOAD 1
    INVOKEINTERFACE java/util/Map.get (Ljava/lang/Object;)Ljava/lang/Object;
    CHECKCAST net/minecraft/nbt/NBTBase$NBTPrimitive
    INVOKEVIRTUAL net/minecraft/nbt/NBTBase$NBTPrimitive.getLong ()J
   L1
   FRAME FULL [net/minecraft/nbt/NBTTagCompound java/lang/String] [J]
    LRETURN
   L2
    LINENUMBER 204 L2
   FRAME FULL [net/minecraft/nbt/NBTTagCompound java/lang/String] [java/lang/ClassCastException]
    ASTORE 2
   L4
    LINENUMBER 206 L4
    LCONST_0
    LRETURN
   L5
    LOCALVARIABLE this Lnet/minecraft/nbt/NBTTagCompound; L0 L0 0
    LOCALVARIABLE p_getLong_1_ Ljava/lang/String; L0 L0 1
    LOCALVARIABLE classcastexception Ljava/lang/ClassCastException; L4 L5 2
    LOCALVARIABLE this Lnet/minecraft/nbt/NBTTagCompound; L0 L5 0
    LOCALVARIABLE key Ljava/lang/String; L0 L5 1
    MAXSTACK = 3
    MAXLOCALS = 3

  // access flags 0x1
  public getFloat(Ljava/lang/String;)F
    TRYCATCHBLOCK L0 L1 L2 java/lang/ClassCastException
   L0
    LINENUMBER 214 L0
    ALOAD 0
    ALOAD 1
    BIPUSH 99
    INVOKEVIRTUAL net/minecraft/nbt/NBTTagCompound.hasKey (Ljava/lang/String;I)Z
    IFNE L3
    FCONST_0
    GOTO L1
   L3
   FRAME FULL [net/minecraft/nbt/NBTTagCompound java/lang/String] []
    ALOAD 0
    GETFIELD net/minecraft/nbt/NBTTagCompound.tagMap : Ljava/util/Map;
    ALOAD 1
    INVOKEINTERFACE java/util/Map.get (Ljava/lang/Object;)Ljava/lang/Object;
    CHECKCAST net/minecraft/nbt/NBTBase$NBTPrimitive
    INVOKEVIRTUAL net/minecraft/nbt/NBTBase$NBTPrimitive.getFloat ()F
   L1
   FRAME FULL [net/minecraft/nbt/NBTTagCompound java/lang/String] [F]
    FRETURN
   L2
    LINENUMBER 216 L2
   FRAME FULL [net/minecraft/nbt/NBTTagCompound java/lang/String] [java/lang/ClassCastException]
    ASTORE 2
   L4
    LINENUMBER 218 L4
    FCONST_0
    FRETURN
   L5
    LOCALVARIABLE this Lnet/minecraft/nbt/NBTTagCompound; L0 L0 0
    LOCALVARIABLE p_getFloat_1_ Ljava/lang/String; L0 L0 1
    LOCALVARIABLE classcastexception Ljava/lang/ClassCastException; L4 L5 2
    LOCALVARIABLE this Lnet/minecraft/nbt/NBTTagCompound; L0 L5 0
    LOCALVARIABLE key Ljava/lang/String; L0 L5 1
    MAXSTACK = 3
    MAXLOCALS = 3

  // access flags 0x1
  public getDouble(Ljava/lang/String;)D
    TRYCATCHBLOCK L0 L1 L2 java/lang/ClassCastException
   L0
    LINENUMBER 226 L0
    ALOAD 0
    ALOAD 1
    BIPUSH 99
    INVOKEVIRTUAL net/minecraft/nbt/NBTTagCompound.hasKey (Ljava/lang/String;I)Z
    IFNE L3
    DCONST_0
    GOTO L1
   L3
   FRAME FULL [net/minecraft/nbt/NBTTagCompound java/lang/String] []
    ALOAD 0
    GETFIELD net/minecraft/nbt/NBTTagCompound.tagMap : Ljava/util/Map;
    ALOAD 1
    INVOKEINTERFACE java/util/Map.get (Ljava/lang/Object;)Ljava/lang/Object;
    CHECKCAST net/minecraft/nbt/NBTBase$NBTPrimitive
    INVOKEVIRTUAL net/minecraft/nbt/NBTBase$NBTPrimitive.getDouble ()D
   L1
   FRAME FULL [net/minecraft/nbt/NBTTagCompound java/lang/String] [D]
    DRETURN
   L2
    LINENUMBER 228 L2
   FRAME FULL [net/minecraft/nbt/NBTTagCompound java/lang/String] [java/lang/ClassCastException]
    ASTORE 2
   L4
    LINENUMBER 230 L4
    DCONST_0
    DRETURN
   L5
    LOCALVARIABLE this Lnet/minecraft/nbt/NBTTagCompound; L0 L0 0
    LOCALVARIABLE p_getDouble_1_ Ljava/lang/String; L0 L0 1
    LOCALVARIABLE classcastexception Ljava/lang/ClassCastException; L4 L5 2
    LOCALVARIABLE this Lnet/minecraft/nbt/NBTTagCompound; L0 L5 0
    LOCALVARIABLE key Ljava/lang/String; L0 L5 1
    MAXSTACK = 3
    MAXLOCALS = 3

  // access flags 0x1
  public getString(Ljava/lang/String;)Ljava/lang/String;
    TRYCATCHBLOCK L0 L1 L2 java/lang/ClassCastException
   L0
    LINENUMBER 238 L0
    ALOAD 0
    ALOAD 1
    BIPUSH 8
    INVOKEVIRTUAL net/minecraft/nbt/NBTTagCompound.hasKey (Ljava/lang/String;I)Z
    IFNE L3
    LDC ""
    GOTO L1
   L3
   FRAME FULL [net/minecraft/nbt/NBTTagCompound java/lang/String] []
    ALOAD 0
    GETFIELD net/minecraft/nbt/NBTTagCompound.tagMap : Ljava/util/Map;
    ALOAD 1
    INVOKEINTERFACE java/util/Map.get (Ljava/lang/Object;)Ljava/lang/Object;
    CHECKCAST net/minecraft/nbt/NBTBase
    INVOKEVIRTUAL net/minecraft/nbt/NBTBase.getString ()Ljava/lang/String;
   L1
   FRAME FULL [net/minecraft/nbt/NBTTagCompound java/lang/String] [java/lang/String]
    ARETURN
   L2
    LINENUMBER 240 L2
   FRAME FULL [net/minecraft/nbt/NBTTagCompound java/lang/String] [java/lang/ClassCastException]
    ASTORE 2
   L4
    LINENUMBER 242 L4
    LDC ""
    ARETURN
   L5
    LOCALVARIABLE this Lnet/minecraft/nbt/NBTTagCompound; L0 L0 0
    LOCALVARIABLE p_getString_1_ Ljava/lang/String; L0 L0 1
    LOCALVARIABLE classcastexception Ljava/lang/ClassCastException; L4 L5 2
    LOCALVARIABLE this Lnet/minecraft/nbt/NBTTagCompound; L0 L5 0
    LOCALVARIABLE key Ljava/lang/String; L0 L5 1
    MAXSTACK = 3
    MAXLOCALS = 3

  // access flags 0x1
  public getByteArray(Ljava/lang/String;)[B
    TRYCATCHBLOCK L0 L1 L2 java/lang/ClassCastException
   L0
    LINENUMBER 250 L0
    ALOAD 0
    ALOAD 1
    BIPUSH 7
    INVOKEVIRTUAL net/minecraft/nbt/NBTTagCompound.hasKey (Ljava/lang/String;I)Z
    IFNE L3
    ICONST_0
    NEWARRAY T_BYTE
    GOTO L1
   L3
   FRAME FULL [net/minecraft/nbt/NBTTagCompound java/lang/String] []
    ALOAD 0
    GETFIELD net/minecraft/nbt/NBTTagCompound.tagMap : Ljava/util/Map;
    ALOAD 1
    INVOKEINTERFACE java/util/Map.get (Ljava/lang/Object;)Ljava/lang/Object;
    CHECKCAST net/minecraft/nbt/NBTTagByteArray
    INVOKEVIRTUAL net/minecraft/nbt/NBTTagByteArray.getByteArray ()[B
   L1
   FRAME FULL [net/minecraft/nbt/NBTTagCompound java/lang/String] [[B]
    ARETURN
   L2
    LINENUMBER 252 L2
   FRAME FULL [net/minecraft/nbt/NBTTagCompound java/lang/String] [java/lang/ClassCastException]
    ASTORE 2
   L4
    LINENUMBER 254 L4
    NEW net/minecraft/util/ReportedException
    DUP
    ALOAD 0
    ALOAD 1
    BIPUSH 7
    ALOAD 2
    INVOKESPECIAL net/minecraft/nbt/NBTTagCompound.createCrashReport (Ljava/lang/String;ILjava/lang/ClassCastException;)Lnet/minecraft/crash/CrashReport;
    INVOKESPECIAL net/minecraft/util/ReportedException.<init> (Lnet/minecraft/crash/CrashReport;)V
    ATHROW
   L5
    LOCALVARIABLE this Lnet/minecraft/nbt/NBTTagCompound; L0 L0 0
    LOCALVARIABLE p_getByteArray_1_ Ljava/lang/String; L0 L0 1
    LOCALVARIABLE classcastexception Ljava/lang/ClassCastException; L4 L5 2
    LOCALVARIABLE this Lnet/minecraft/nbt/NBTTagCompound; L0 L5 0
    LOCALVARIABLE key Ljava/lang/String; L0 L5 1
    MAXSTACK = 6
    MAXLOCALS = 3

  // access flags 0x1
  public getIntArray(Ljava/lang/String;)[I
    TRYCATCHBLOCK L0 L1 L2 java/lang/ClassCastException
   L0
    LINENUMBER 262 L0
    ALOAD 0
    ALOAD 1
    BIPUSH 11
    INVOKEVIRTUAL net/minecraft/nbt/NBTTagCompound.hasKey (Ljava/lang/String;I)Z
    IFNE L3
    ICONST_0
    NEWARRAY T_INT
    GOTO L1
   L3
   FRAME FULL [net/minecraft/nbt/NBTTagCompound java/lang/String] []
    ALOAD 0
    GETFIELD net/minecraft/nbt/NBTTagCompound.tagMap : Ljava/util/Map;
    ALOAD 1
    INVOKEINTERFACE java/util/Map.get (Ljava/lang/Object;)Ljava/lang/Object;
    CHECKCAST net/minecraft/nbt/NBTTagIntArray
    INVOKEVIRTUAL net/minecraft/nbt/NBTTagIntArray.getIntArray ()[I
   L1
   FRAME FULL [net/minecraft/nbt/NBTTagCompound java/lang/String] [[I]
    ARETURN
   L2
    LINENUMBER 264 L2
   FRAME FULL [net/minecraft/nbt/NBTTagCompound java/lang/String] [java/lang/ClassCastException]
    ASTORE 2
   L4
    LINENUMBER 266 L4
    NEW net/minecraft/util/ReportedException
    DUP
    ALOAD 0
    ALOAD 1
    BIPUSH 11
    ALOAD 2
    INVOKESPECIAL net/minecraft/nbt/NBTTagCompound.createCrashReport (Ljava/lang/String;ILjava/lang/ClassCastException;)Lnet/minecraft/crash/CrashReport;
    INVOKESPECIAL net/minecraft/util/ReportedException.<init> (Lnet/minecraft/crash/CrashReport;)V
    ATHROW
   L5
    LOCALVARIABLE this Lnet/minecraft/nbt/NBTTagCompound; L0 L0 0
    LOCALVARIABLE p_getIntArray_1_ Ljava/lang/String; L0 L0 1
    LOCALVARIABLE classcastexception Ljava/lang/ClassCastException; L4 L5 2
    LOCALVARIABLE this Lnet/minecraft/nbt/NBTTagCompound; L0 L5 0
    LOCALVARIABLE key Ljava/lang/String; L0 L5 1
    MAXSTACK = 6
    MAXLOCALS = 3

  // access flags 0x1
  public getCompoundTag(Ljava/lang/String;)Lnet/minecraft/nbt/NBTTagCompound;
    TRYCATCHBLOCK L0 L1 L2 java/lang/ClassCastException
   L0
    LINENUMBER 274 L0
    ALOAD 0
    ALOAD 1
    BIPUSH 10
    INVOKEVIRTUAL net/minecraft/nbt/NBTTagCompound.hasKey (Ljava/lang/String;I)Z
    IFNE L3
    NEW net/minecraft/nbt/NBTTagCompound
    DUP
    INVOKESPECIAL net/minecraft/nbt/NBTTagCompound.<init> ()V
    GOTO L1
   L3
   FRAME FULL [net/minecraft/nbt/NBTTagCompound java/lang/String] []
    ALOAD 0
    GETFIELD net/minecraft/nbt/NBTTagCompound.tagMap : Ljava/util/Map;
    ALOAD 1
    INVOKEINTERFACE java/util/Map.get (Ljava/lang/Object;)Ljava/lang/Object;
    CHECKCAST net/minecraft/nbt/NBTTagCompound
   L1
   FRAME FULL [net/minecraft/nbt/NBTTagCompound java/lang/String] [net/minecraft/nbt/NBTTagCompound]
    ARETURN
   L2
    LINENUMBER 276 L2
   FRAME FULL [net/minecraft/nbt/NBTTagCompound java/lang/String] [java/lang/ClassCastException]
    ASTORE 2
   L4
    LINENUMBER 278 L4
    NEW net/minecraft/util/ReportedException
    DUP
    ALOAD 0
    ALOAD 1
    BIPUSH 10
    ALOAD 2
    INVOKESPECIAL net/minecraft/nbt/NBTTagCompound.createCrashReport (Ljava/lang/String;ILjava/lang/ClassCastException;)Lnet/minecraft/crash/CrashReport;
    INVOKESPECIAL net/minecraft/util/ReportedException.<init> (Lnet/minecraft/crash/CrashReport;)V
    ATHROW
   L5
    LOCALVARIABLE this Lnet/minecraft/nbt/NBTTagCompound; L0 L0 0
    LOCALVARIABLE p_getCompoundTag_1_ Ljava/lang/String; L0 L0 1
    LOCALVARIABLE classcastexception Ljava/lang/ClassCastException; L4 L5 2
    LOCALVARIABLE this Lnet/minecraft/nbt/NBTTagCompound; L0 L5 0
    LOCALVARIABLE key Ljava/lang/String; L0 L5 1
    MAXSTACK = 6
    MAXLOCALS = 3

  // access flags 0x1
  public getTagList(Ljava/lang/String;I)Lnet/minecraft/nbt/NBTTagList;
    TRYCATCHBLOCK L0 L1 L2 java/lang/ClassCastException
    TRYCATCHBLOCK L3 L4 L2 java/lang/ClassCastException
   L0
    LINENUMBER 286 L0
    ALOAD 0
    ALOAD 1
    INVOKEVIRTUAL net/minecraft/nbt/NBTTagCompound.getTagId (Ljava/lang/String;)B
    BIPUSH 9
    IF_ICMPEQ L3
   L5
    LINENUMBER 288 L5
    NEW net/minecraft/nbt/NBTTagList
    DUP
    INVOKESPECIAL net/minecraft/nbt/NBTTagList.<init> ()V
   L1
    ARETURN
   L3
    LINENUMBER 292 L3
   FRAME FULL [net/minecraft/nbt/NBTTagCompound java/lang/String I] []
    ALOAD 0
    GETFIELD net/minecraft/nbt/NBTTagCompound.tagMap : Ljava/util/Map;
    ALOAD 1
    INVOKEINTERFACE java/util/Map.get (Ljava/lang/Object;)Ljava/lang/Object;
    CHECKCAST net/minecraft/nbt/NBTTagList
    ASTORE 3
   L6
    LINENUMBER 293 L6
    ALOAD 3
    INVOKEVIRTUAL net/minecraft/nbt/NBTTagList.tagCount ()I
    IFLE L7
    ALOAD 3
    INVOKEVIRTUAL net/minecraft/nbt/NBTTagList.getTagType ()I
    ILOAD 2
    IF_ICMPEQ L7
    NEW net/minecraft/nbt/NBTTagList
    DUP
    INVOKESPECIAL net/minecraft/nbt/NBTTagList.<init> ()V
    GOTO L4
   L7
   FRAME FULL [net/minecraft/nbt/NBTTagCompound java/lang/String I net/minecraft/nbt/NBTTagList] []
    ALOAD 3
   L4
   FRAME FULL [net/minecraft/nbt/NBTTagCompound java/lang/String I net/minecraft/nbt/NBTTagList] [net/minecraft/nbt/NBTTagList]
    ARETURN
   L2
    LINENUMBER 296 L2
   FRAME FULL [net/minecraft/nbt/NBTTagCompound java/lang/String I] [java/lang/ClassCastException]
    ASTORE 3
   L8
    LINENUMBER 298 L8
    NEW net/minecraft/util/ReportedException
    DUP
    ALOAD 0
    ALOAD 1
    BIPUSH 9
    ALOAD 3
    INVOKESPECIAL net/minecraft/nbt/NBTTagCompound.createCrashReport (Ljava/lang/String;ILjava/lang/ClassCastException;)Lnet/minecraft/crash/CrashReport;
    INVOKESPECIAL net/minecraft/util/ReportedException.<init> (Lnet/minecraft/crash/CrashReport;)V
    ATHROW
   L9
    LOCALVARIABLE this Lnet/minecraft/nbt/NBTTagCompound; L0 L0 0
    LOCALVARIABLE p_getTagList_1_ Ljava/lang/String; L0 L0 1
    LOCALVARIABLE p_getTagList_2_ I L0 L0 2
    LOCALVARIABLE nbttaglist Lnet/minecraft/nbt/NBTTagList; L6 L2 3
    LOCALVARIABLE classcastexception Ljava/lang/ClassCastException; L8 L9 3
    LOCALVARIABLE this Lnet/minecraft/nbt/NBTTagCompound; L0 L9 0
    LOCALVARIABLE key Ljava/lang/String; L0 L9 1
    LOCALVARIABLE type I L0 L9 2
    MAXSTACK = 6
    MAXLOCALS = 4

  // access flags 0x1
  public getBoolean(Ljava/lang/String;)Z
   L0
    LINENUMBER 304 L0
    ALOAD 0
    ALOAD 1
    INVOKEVIRTUAL net/minecraft/nbt/NBTTagCompound.getByte (Ljava/lang/String;)B
    IFEQ L1
    ICONST_1
    GOTO L2
   L1
   FRAME FULL [net/minecraft/nbt/NBTTagCompound java/lang/String] []
    ICONST_0
   L2
   FRAME FULL [net/minecraft/nbt/NBTTagCompound java/lang/String] [I]
    IRETURN
   L3
    LOCALVARIABLE this Lnet/minecraft/nbt/NBTTagCompound; L0 L0 0
    LOCALVARIABLE p_getBoolean_1_ Ljava/lang/String; L0 L0 1
    LOCALVARIABLE this Lnet/minecraft/nbt/NBTTagCompound; L0 L3 0
    LOCALVARIABLE key Ljava/lang/String; L0 L3 1
    MAXSTACK = 2
    MAXLOCALS = 2

  // access flags 0x1
  public removeTag(Ljava/lang/String;)V
   L0
    LINENUMBER 309 L0
    ALOAD 0
    GETFIELD net/minecraft/nbt/NBTTagCompound.tagMap : Ljava/util/Map;
    ALOAD 1
    INVOKEINTERFACE java/util/Map.remove (Ljava/lang/Object;)Ljava/lang/Object;
    POP
   L1
    LINENUMBER 310 L1
    RETURN
   L2
    LOCALVARIABLE this Lnet/minecraft/nbt/NBTTagCompound; L0 L0 0
    LOCALVARIABLE p_removeTag_1_ Ljava/lang/String; L0 L0 1
    LOCALVARIABLE this Lnet/minecraft/nbt/NBTTagCompound; L0 L2 0
    LOCALVARIABLE key Ljava/lang/String; L0 L2 1
    MAXSTACK = 2
    MAXLOCALS = 2

  // access flags 0x1
  public toString()Ljava/lang/String;
   L0
    LINENUMBER 314 L0
    LDC "{"
    ASTORE 1
   L1
    LINENUMBER 317 L1
    ALOAD 0
    GETFIELD net/minecraft/nbt/NBTTagCompound.tagMap : Ljava/util/Map;
    INVOKEINTERFACE java/util/Map.keySet ()Ljava/util/Set;
    INVOKEINTERFACE java/util/Set.iterator ()Ljava/util/Iterator;
    ASTORE 2
   L2
   FRAME FULL [net/minecraft/nbt/NBTTagCompound java/lang/String java/util/Iterator] []
    ALOAD 2
    INVOKEINTERFACE java/util/Iterator.hasNext ()Z
    IFEQ L3
   L4
    LINENUMBER 319 L4
    ALOAD 2
    INVOKEINTERFACE java/util/Iterator.next ()Ljava/lang/Object;
    CHECKCAST java/lang/String
    ASTORE 3
   L5
    LINENUMBER 317 L5
    NEW java/lang/StringBuilder
    DUP
    INVOKESPECIAL java/lang/StringBuilder.<init> ()V
    ALOAD 1
    INVOKEVIRTUAL java/lang/StringBuilder.append (Ljava/lang/String;)Ljava/lang/StringBuilder;
    ALOAD 3
    INVOKEVIRTUAL java/lang/StringBuilder.append (Ljava/lang/String;)Ljava/lang/StringBuilder;
    BIPUSH 58
    INVOKEVIRTUAL java/lang/StringBuilder.append (C)Ljava/lang/StringBuilder;
    ALOAD 0
    GETFIELD net/minecraft/nbt/NBTTagCompound.tagMap : Ljava/util/Map;
    ALOAD 3
    INVOKEINTERFACE java/util/Map.get (Ljava/lang/Object;)Ljava/lang/Object;
    INVOKEVIRTUAL java/lang/StringBuilder.append (Ljava/lang/Object;)Ljava/lang/StringBuilder;
    BIPUSH 44
    INVOKEVIRTUAL java/lang/StringBuilder.append (C)Ljava/lang/StringBuilder;
    INVOKEVIRTUAL java/lang/StringBuilder.toString ()Ljava/lang/String;
    ASTORE 1
    GOTO L2
   L3
    LINENUMBER 322 L3
   FRAME FULL [net/minecraft/nbt/NBTTagCompound java/lang/String java/util/Iterator] []
    NEW java/lang/StringBuilder
    DUP
    INVOKESPECIAL java/lang/StringBuilder.<init> ()V
    ALOAD 1
    INVOKEVIRTUAL java/lang/StringBuilder.append (Ljava/lang/String;)Ljava/lang/StringBuilder;
    INVOKESTATIC codechicken/nei/NEIServerUtils.fixTrailingCommaList (Ljava/lang/StringBuilder;)Ljava/lang/StringBuilder;
    LDC "}"
    INVOKEVIRTUAL java/lang/StringBuilder.append (Ljava/lang/String;)Ljava/lang/StringBuilder;
    INVOKEVIRTUAL java/lang/StringBuilder.toString ()Ljava/lang/String;
    ARETURN
   L6
    LOCALVARIABLE s1 Ljava/lang/String; L5 L3 3
    LOCALVARIABLE iterator Ljava/util/Iterator; L2 L3 2
    LOCALVARIABLE this Lnet/minecraft/nbt/NBTTagCompound; L0 L6 0
    LOCALVARIABLE s Ljava/lang/String; L1 L6 1
    MAXSTACK = 3
    MAXLOCALS = 4

  // access flags 0x1
  public hasNoTags()Z
   L0
    LINENUMBER 327 L0
    ALOAD 0
    GETFIELD net/minecraft/nbt/NBTTagCompound.tagMap : Ljava/util/Map;
    INVOKEINTERFACE java/util/Map.isEmpty ()Z
    IRETURN
   L1
    LOCALVARIABLE this Lnet/minecraft/nbt/NBTTagCompound; L0 L1 0
    MAXSTACK = 1
    MAXLOCALS = 1

  // access flags 0x2
  private createCrashReport(Ljava/lang/String;ILjava/lang/ClassCastException;)Lnet/minecraft/crash/CrashReport;
   L0
    LINENUMBER 332 L0
    ALOAD 3
    LDC "Reading NBT data"
    INVOKESTATIC net/minecraft/crash/CrashReport.makeCrashReport (Ljava/lang/Throwable;Ljava/lang/String;)Lnet/minecraft/crash/CrashReport;
    ASTORE 4
   L1
    LINENUMBER 333 L1
    ALOAD 4
    LDC "Corrupt NBT tag"
    ICONST_1
    INVOKEVIRTUAL net/minecraft/crash/CrashReport.makeCategoryDepth (Ljava/lang/String;I)Lnet/minecraft/crash/CrashReportCategory;
    ASTORE 5
   L2
    LINENUMBER 334 L2
    ALOAD 5
    LDC "Tag type found"
    NEW net/minecraft/nbt/NBTTagCompound$1
    DUP
    ALOAD 0
    ALOAD 1
    INVOKESPECIAL net/minecraft/nbt/NBTTagCompound$1.<init> (Lnet/minecraft/nbt/NBTTagCompound;Ljava/lang/String;)V
    INVOKEVIRTUAL net/minecraft/crash/CrashReportCategory.addCrashSectionCallable (Ljava/lang/String;Ljava/util/concurrent/Callable;)V
   L3
    LINENUMBER 342 L3
    ALOAD 5
    LDC "Tag type expected"
    NEW net/minecraft/nbt/NBTTagCompound$2
    DUP
    ALOAD 0
    ILOAD 2
    INVOKESPECIAL net/minecraft/nbt/NBTTagCompound$2.<init> (Lnet/minecraft/nbt/NBTTagCompound;I)V
    INVOKEVIRTUAL net/minecraft/crash/CrashReportCategory.addCrashSectionCallable (Ljava/lang/String;Ljava/util/concurrent/Callable;)V
   L4
    LINENUMBER 350 L4
    ALOAD 5
    LDC "Tag name"
    ALOAD 1
    INVOKEVIRTUAL net/minecraft/crash/CrashReportCategory.addCrashSection (Ljava/lang/String;Ljava/lang/Object;)V
   L5
    LINENUMBER 351 L5
    ALOAD 4
    ARETURN
   L6
    LOCALVARIABLE this Lnet/minecraft/nbt/NBTTagCompound; L0 L0 0
    LOCALVARIABLE p_createCrashReport_1_ Ljava/lang/String; L0 L0 1
    LOCALVARIABLE p_createCrashReport_2_ I L0 L0 2
    LOCALVARIABLE p_createCrashReport_3_ Ljava/lang/ClassCastException; L0 L0 3
    LOCALVARIABLE this Lnet/minecraft/nbt/NBTTagCompound; L0 L6 0
    LOCALVARIABLE key Ljava/lang/String; L0 L6 1
    LOCALVARIABLE expectedType I L0 L6 2
    LOCALVARIABLE ex Ljava/lang/ClassCastException; L0 L6 3
    LOCALVARIABLE crashreport Lnet/minecraft/crash/CrashReport; L1 L6 4
    LOCALVARIABLE crashreportcategory Lnet/minecraft/crash/CrashReportCategory; L2 L6 5
    MAXSTACK = 6
    MAXLOCALS = 6

  // access flags 0x1
  public copy()Lnet/minecraft/nbt/NBTBase;
   L0
    LINENUMBER 356 L0
    NEW net/minecraft/nbt/NBTTagCompound
    DUP
    INVOKESPECIAL net/minecraft/nbt/NBTTagCompound.<init> ()V
    ASTORE 1
   L1
    LINENUMBER 357 L1
    ALOAD 0
    GETFIELD net/minecraft/nbt/NBTTagCompound.tagMap : Ljava/util/Map;
    INVOKEINTERFACE java/util/Map.keySet ()Ljava/util/Set;
    INVOKEINTERFACE java/util/Set.iterator ()Ljava/util/Iterator;
    ASTORE 2
   L2
    LINENUMBER 359 L2
   FRAME FULL [net/minecraft/nbt/NBTTagCompound net/minecraft/nbt/NBTTagCompound java/util/Iterator] []
    ALOAD 2
    INVOKEINTERFACE java/util/Iterator.hasNext ()Z
    IFEQ L3
   L4
    LINENUMBER 361 L4
    ALOAD 2
    INVOKEINTERFACE java/util/Iterator.next ()Ljava/lang/Object;
    CHECKCAST java/lang/String
    ASTORE 3
   L5
    LINENUMBER 362 L5
    ALOAD 1
    ALOAD 3
    ALOAD 0
    GETFIELD net/minecraft/nbt/NBTTagCompound.tagMap : Ljava/util/Map;
    ALOAD 3
    INVOKEINTERFACE java/util/Map.get (Ljava/lang/Object;)Ljava/lang/Object;
    CHECKCAST net/minecraft/nbt/NBTBase
    INVOKEVIRTUAL net/minecraft/nbt/NBTBase.copy ()Lnet/minecraft/nbt/NBTBase;
    INVOKEVIRTUAL net/minecraft/nbt/NBTTagCompound.setTag (Ljava/lang/String;Lnet/minecraft/nbt/NBTBase;)V
   L6
    LINENUMBER 363 L6
    GOTO L2
   L3
    LINENUMBER 365 L3
   FRAME FULL [net/minecraft/nbt/NBTTagCompound net/minecraft/nbt/NBTTagCompound java/util/Iterator] []
    ALOAD 1
    ARETURN
   L7
    LOCALVARIABLE s Ljava/lang/String; L5 L6 3
    LOCALVARIABLE this Lnet/minecraft/nbt/NBTTagCompound; L0 L7 0
    LOCALVARIABLE nbttagcompound Lnet/minecraft/nbt/NBTTagCompound; L1 L7 1
    LOCALVARIABLE iterator Ljava/util/Iterator; L2 L7 2
    MAXSTACK = 4
    MAXLOCALS = 4

  // access flags 0x1
  public equals(Ljava/lang/Object;)Z
   L0
    LINENUMBER 370 L0
    ALOAD 0
    ALOAD 1
    INVOKESPECIAL net/minecraft/nbt/NBTBase.equals (Ljava/lang/Object;)Z
    IFEQ L1
   L2
    LINENUMBER 372 L2
    ALOAD 1
    CHECKCAST net/minecraft/nbt/NBTTagCompound
    ASTORE 2
   L3
    LINENUMBER 373 L3
    ALOAD 0
    GETFIELD net/minecraft/nbt/NBTTagCompound.tagMap : Ljava/util/Map;
    INVOKEINTERFACE java/util/Map.entrySet ()Ljava/util/Set;
    ALOAD 2
    GETFIELD net/minecraft/nbt/NBTTagCompound.tagMap : Ljava/util/Map;
    INVOKEINTERFACE java/util/Map.entrySet ()Ljava/util/Set;
    INVOKEINTERFACE java/util/Set.equals (Ljava/lang/Object;)Z
    IRETURN
   L1
    LINENUMBER 377 L1
   FRAME FULL [net/minecraft/nbt/NBTTagCompound java/lang/Object] []
    ICONST_0
    IRETURN
   L4
    LOCALVARIABLE this Lnet/minecraft/nbt/NBTTagCompound; L0 L0 0
    LOCALVARIABLE p_equals_1_ Ljava/lang/Object; L0 L0 1
    LOCALVARIABLE nbttagcompound Lnet/minecraft/nbt/NBTTagCompound; L3 L1 2
    LOCALVARIABLE this Lnet/minecraft/nbt/NBTTagCompound; L0 L4 0
    LOCALVARIABLE p_equals_1_ Ljava/lang/Object; L0 L4 1
    MAXSTACK = 2
    MAXLOCALS = 3

  // access flags 0x1
  public hashCode()I
   L0
    LINENUMBER 383 L0
    ALOAD 0
    INVOKESPECIAL net/minecraft/nbt/NBTBase.hashCode ()I
    ALOAD 0
    GETFIELD net/minecraft/nbt/NBTTagCompound.tagMap : Ljava/util/Map;
    INVOKEINTERFACE java/util/Map.hashCode ()I
    IXOR
    IRETURN
   L1
    LOCALVARIABLE this Lnet/minecraft/nbt/NBTTagCompound; L0 L1 0
    MAXSTACK = 2
    MAXLOCALS = 1

  // access flags 0xA
  private static writeEntry(Ljava/lang/String;Lnet/minecraft/nbt/NBTBase;Ljava/io/DataOutput;)V throws java/io/IOException 
   L0
    LINENUMBER 388 L0
    ALOAD 2
    ALOAD 1
    INVOKEVIRTUAL net/minecraft/nbt/NBTBase.getId ()B
    INVOKEINTERFACE java/io/DataOutput.writeByte (I)V
   L1
    LINENUMBER 390 L1
    ALOAD 1
    INVOKEVIRTUAL net/minecraft/nbt/NBTBase.getId ()B
    IFEQ L2
   L3
    LINENUMBER 392 L3
    ALOAD 2
    ALOAD 0
    INVOKEINTERFACE java/io/DataOutput.writeUTF (Ljava/lang/String;)V
   L4
    LINENUMBER 393 L4
    ALOAD 1
    ALOAD 2
    INVOKEVIRTUAL net/minecraft/nbt/NBTBase.write (Ljava/io/DataOutput;)V
   L2
    LINENUMBER 395 L2
   FRAME FULL [java/lang/String net/minecraft/nbt/NBTBase java/io/DataOutput] []
    RETURN
   L5
    LOCALVARIABLE p_writeEntry_0_ Ljava/lang/String; L0 L0 0
    LOCALVARIABLE p_writeEntry_1_ Lnet/minecraft/nbt/NBTBase; L0 L0 1
    LOCALVARIABLE p_writeEntry_2_ Ljava/io/DataOutput; L0 L0 2
    LOCALVARIABLE name Ljava/lang/String; L0 L5 0
    LOCALVARIABLE data Lnet/minecraft/nbt/NBTBase; L0 L5 1
    LOCALVARIABLE output Ljava/io/DataOutput; L0 L5 2
    MAXSTACK = 2
    MAXLOCALS = 3

  // access flags 0xA
  private static readType(Ljava/io/DataInput;Lnet/minecraft/nbt/NBTSizeTracker;)B throws java/io/IOException 
   L0
    LINENUMBER 399 L0
    ALOAD 1
    LDC 8
    INVOKEVIRTUAL net/minecraft/nbt/NBTSizeTracker.read (J)V
   L1
    LINENUMBER 400 L1
    ALOAD 0
    INVOKEINTERFACE java/io/DataInput.readByte ()B
    IRETURN
   L2
    LOCALVARIABLE p_readType_0_ Ljava/io/DataInput; L0 L0 0
    LOCALVARIABLE p_readType_1_ Lnet/minecraft/nbt/NBTSizeTracker; L0 L0 1
    LOCALVARIABLE input Ljava/io/DataInput; L0 L2 0
    LOCALVARIABLE sizeTracker Lnet/minecraft/nbt/NBTSizeTracker; L0 L2 1
    MAXSTACK = 3
    MAXLOCALS = 2

  // access flags 0xA
  private static readKey(Ljava/io/DataInput;Lnet/minecraft/nbt/NBTSizeTracker;)Ljava/lang/String; throws java/io/IOException 
   L0
    LINENUMBER 405 L0
    ALOAD 0
    INVOKEINTERFACE java/io/DataInput.readUTF ()Ljava/lang/String;
    ARETURN
   L1
    LOCALVARIABLE p_readKey_0_ Ljava/io/DataInput; L0 L0 0
    LOCALVARIABLE p_readKey_1_ Lnet/minecraft/nbt/NBTSizeTracker; L0 L0 1
    LOCALVARIABLE input Ljava/io/DataInput; L0 L1 0
    LOCALVARIABLE sizeTracker Lnet/minecraft/nbt/NBTSizeTracker; L0 L1 1
    MAXSTACK = 1
    MAXLOCALS = 2

  // access flags 0x8
  static readNBT(BLjava/lang/String;Ljava/io/DataInput;ILnet/minecraft/nbt/NBTSizeTracker;)Lnet/minecraft/nbt/NBTBase;
    TRYCATCHBLOCK L0 L1 L2 java/io/IOException
   L3
    LINENUMBER 410 L3
    ALOAD 4
    LDC 32
    INVOKEVIRTUAL net/minecraft/nbt/NBTSizeTracker.read (J)V
   L4
    LINENUMBER 411 L4
    ILOAD 0
    INVOKESTATIC net/minecraft/nbt/NBTBase.createNewByType (B)Lnet/minecraft/nbt/NBTBase;
    ASTORE 5
   L0
    LINENUMBER 415 L0
    ALOAD 5
    ALOAD 2
    ILOAD 3
    ALOAD 4
    INVOKEVIRTUAL net/minecraft/nbt/NBTBase.read (Ljava/io/DataInput;ILnet/minecraft/nbt/NBTSizeTracker;)V
   L5
    LINENUMBER 416 L5
    ALOAD 5
   L1
    ARETURN
   L2
    LINENUMBER 418 L2
   FRAME FULL [I java/lang/String java/io/DataInput I net/minecraft/nbt/NBTSizeTracker net/minecraft/nbt/NBTBase] [java/io/IOException]
    ASTORE 6
   L6
    LINENUMBER 420 L6
    ALOAD 6
    LDC "Loading NBT data"
    INVOKESTATIC net/minecraft/crash/CrashReport.makeCrashReport (Ljava/lang/Throwable;Ljava/lang/String;)Lnet/minecraft/crash/CrashReport;
    ASTORE 7
   L7
    LINENUMBER 421 L7
    ALOAD 7
    LDC "NBT Tag"
    INVOKEVIRTUAL net/minecraft/crash/CrashReport.makeCategory (Ljava/lang/String;)Lnet/minecraft/crash/CrashReportCategory;
    ASTORE 8
   L8
    LINENUMBER 422 L8
    ALOAD 8
    LDC "Tag name"
    ALOAD 1
    INVOKEVIRTUAL net/minecraft/crash/CrashReportCategory.addCrashSection (Ljava/lang/String;Ljava/lang/Object;)V
   L9
    LINENUMBER 423 L9
    ALOAD 8
    LDC "Tag type"
    ILOAD 0
    INVOKESTATIC java/lang/Byte.valueOf (B)Ljava/lang/Byte;
    INVOKEVIRTUAL net/minecraft/crash/CrashReportCategory.addCrashSection (Ljava/lang/String;Ljava/lang/Object;)V
   L10
    LINENUMBER 424 L10
    NEW net/minecraft/util/ReportedException
    DUP
    ALOAD 7
    INVOKESPECIAL net/minecraft/util/ReportedException.<init> (Lnet/minecraft/crash/CrashReport;)V
    ATHROW
   L11
    LOCALVARIABLE p_readNBT_0_ B L3 L3 0
    LOCALVARIABLE p_readNBT_1_ Ljava/lang/String; L3 L3 1
    LOCALVARIABLE p_readNBT_2_ Ljava/io/DataInput; L3 L3 2
    LOCALVARIABLE p_readNBT_3_ I L3 L3 3
    LOCALVARIABLE p_readNBT_4_ Lnet/minecraft/nbt/NBTSizeTracker; L3 L3 4
    LOCALVARIABLE crashreport Lnet/minecraft/crash/CrashReport; L7 L11 7
    LOCALVARIABLE crashreportcategory Lnet/minecraft/crash/CrashReportCategory; L8 L11 8
    LOCALVARIABLE ioexception Ljava/io/IOException; L6 L11 6
    LOCALVARIABLE id B L3 L11 0
    LOCALVARIABLE key Ljava/lang/String; L3 L11 1
    LOCALVARIABLE input Ljava/io/DataInput; L3 L11 2
    LOCALVARIABLE depth I L3 L11 3
    LOCALVARIABLE sizeTracker Lnet/minecraft/nbt/NBTSizeTracker; L3 L11 4
    LOCALVARIABLE nbtbase Lnet/minecraft/nbt/NBTBase; L0 L11 5
    MAXSTACK = 4
    MAXLOCALS = 9

  // access flags 0x1
  public merge(Lnet/minecraft/nbt/NBTTagCompound;)V
   L0
    LINENUMBER 430 L0
    ALOAD 1
    GETFIELD net/minecraft/nbt/NBTTagCompound.tagMap : Ljava/util/Map;
    INVOKEINTERFACE java/util/Map.keySet ()Ljava/util/Set;
    INVOKEINTERFACE java/util/Set.iterator ()Ljava/util/Iterator;
    ASTORE 2
   L1
    LINENUMBER 432 L1
   FRAME FULL [net/minecraft/nbt/NBTTagCompound net/minecraft/nbt/NBTTagCompound java/util/Iterator] []
    ALOAD 2
    INVOKEINTERFACE java/util/Iterator.hasNext ()Z
    IFEQ L2
   L3
    LINENUMBER 434 L3
    ALOAD 2
    INVOKEINTERFACE java/util/Iterator.next ()Ljava/lang/Object;
    CHECKCAST java/lang/String
    ASTORE 3
   L4
    LINENUMBER 435 L4
    ALOAD 1
    GETFIELD net/minecraft/nbt/NBTTagCompound.tagMap : Ljava/util/Map;
    ALOAD 3
    INVOKEINTERFACE java/util/Map.get (Ljava/lang/Object;)Ljava/lang/Object;
    CHECKCAST net/minecraft/nbt/NBTBase
    ASTORE 4
   L5
    LINENUMBER 437 L5
    ALOAD 4
    INVOKEVIRTUAL net/minecraft/nbt/NBTBase.getId ()B
    BIPUSH 10
    IF_ICMPNE L6
   L7
    LINENUMBER 439 L7
    ALOAD 0
    ALOAD 3
    BIPUSH 10
    INVOKEVIRTUAL net/minecraft/nbt/NBTTagCompound.hasKey (Ljava/lang/String;I)Z
    IFEQ L8
   L9
    LINENUMBER 441 L9
    ALOAD 0
    ALOAD 3
    INVOKEVIRTUAL net/minecraft/nbt/NBTTagCompound.getCompoundTag (Ljava/lang/String;)Lnet/minecraft/nbt/NBTTagCompound;
    ASTORE 5
   L10
    LINENUMBER 442 L10
    ALOAD 5
    ALOAD 4
    CHECKCAST net/minecraft/nbt/NBTTagCompound
    INVOKEVIRTUAL net/minecraft/nbt/NBTTagCompound.merge (Lnet/minecraft/nbt/NBTTagCompound;)V
   L11
    LINENUMBER 443 L11
    GOTO L12
   L8
    LINENUMBER 446 L8
   FRAME FULL [net/minecraft/nbt/NBTTagCompound net/minecraft/nbt/NBTTagCompound java/util/Iterator java/lang/String net/minecraft/nbt/NBTBase] []
    ALOAD 0
    ALOAD 3
    ALOAD 4
    INVOKEVIRTUAL net/minecraft/nbt/NBTBase.copy ()Lnet/minecraft/nbt/NBTBase;
    INVOKEVIRTUAL net/minecraft/nbt/NBTTagCompound.setTag (Ljava/lang/String;Lnet/minecraft/nbt/NBTBase;)V
    GOTO L12
   L6
    LINENUMBER 451 L6
   FRAME FULL [net/minecraft/nbt/NBTTagCompound net/minecraft/nbt/NBTTagCompound java/util/Iterator java/lang/String net/minecraft/nbt/NBTBase] []
    ALOAD 0
    ALOAD 3
    ALOAD 4
    INVOKEVIRTUAL net/minecraft/nbt/NBTBase.copy ()Lnet/minecraft/nbt/NBTBase;
    INVOKEVIRTUAL net/minecraft/nbt/NBTTagCompound.setTag (Ljava/lang/String;Lnet/minecraft/nbt/NBTBase;)V
   L12
    LINENUMBER 453 L12
   FRAME FULL [net/minecraft/nbt/NBTTagCompound net/minecraft/nbt/NBTTagCompound java/util/Iterator java/lang/String net/minecraft/nbt/NBTBase] []
    GOTO L1
   L2
    LINENUMBER 454 L2
   FRAME FULL [net/minecraft/nbt/NBTTagCompound net/minecraft/nbt/NBTTagCompound java/util/Iterator] []
    RETURN
   L13
    LOCALVARIABLE this Lnet/minecraft/nbt/NBTTagCompound; L0 L0 0
    LOCALVARIABLE p_merge_1_ Lnet/minecraft/nbt/NBTTagCompound; L0 L0 1
    LOCALVARIABLE nbttagcompound1 Lnet/minecraft/nbt/NBTTagCompound; L10 L11 5
    LOCALVARIABLE s Ljava/lang/String; L4 L12 3
    LOCALVARIABLE nbtbase Lnet/minecraft/nbt/NBTBase; L5 L12 4
    LOCALVARIABLE this Lnet/minecraft/nbt/NBTTagCompound; L0 L13 0
    LOCALVARIABLE other Lnet/minecraft/nbt/NBTTagCompound; L0 L13 1
    LOCALVARIABLE iterator Ljava/util/Iterator; L1 L13 2
    MAXSTACK = 3
    MAXLOCALS = 6

  // access flags 0x8
  static access$000(Lnet/minecraft/nbt/NBTTagCompound;)Ljava/util/Map;
   L0
    LINENUMBER 17 L0
    ALOAD 0
    GETFIELD net/minecraft/nbt/NBTTagCompound.tagMap : Ljava/util/Map;
    ARETURN
   L1
    LOCALVARIABLE p_access$000_0_ Lnet/minecraft/nbt/NBTTagCompound; L0 L0 0
    LOCALVARIABLE x0 Lnet/minecraft/nbt/NBTTagCompound; L0 L1 0
    MAXSTACK = 1
    MAXLOCALS = 1

  // access flags 0x8
  static <clinit>()V
   L0
    LINENUMBER 19 L0
    INVOKESTATIC org/apache/logging/log4j/LogManager.getLogger ()Lorg/apache/logging/log4j/Logger;
    PUTSTATIC net/minecraft/nbt/NBTTagCompound.logger : Lorg/apache/logging/log4j/Logger;
    RETURN
    MAXSTACK = 1
    MAXLOCALS = 0
}
